niceprint.py
niceprint-3.4.0.dist-info/METADATA
niceprint-3.4.0.dist-info/WHEEL
niceprint-3.4.0.dist-info/top_level.txt
niceprint-3.4.0.dist-info/RECORD
