Metadata-Version: 2.1
Name: niceprint
Version: 3.4.0
Summary: A minute package for formating output
Home-page: https://niceprint.readthedocs.io/en/latest/
Author: AstralDev
Author-email: ekureedem480@gmail.com
License: MIT
Classifier: Development Status :: 3 - Alpha
Classifier: Programming Language :: Python :: 3.7
Classifier: Environment :: Console
Classifier: License :: OSI Approved :: MIT License
Requires-Python: >=3
